HashLibrary/HashLibrary.py
HashLibrary/__init__.py
robotframework_hashlibrary-0.3.dist-info/LICENSE
robotframework_hashlibrary-0.3.dist-info/METADATA
robotframework_hashlibrary-0.3.dist-info/WHEEL
robotframework_hashlibrary-0.3.dist-info/top_level.txt
robotframework_hashlibrary-0.3.dist-info/RECORD
